autograd/__init__.py
autograd/core/Graph.py
autograd/core/Spares_nn.py
autograd/core/__init__.py
autograd/core/engine.py
autograd/core/nn.py
autograd/torch/__init__.py
autograd/torch/init.py
autograd/torch/tensor.py
autograd/torch/nn/__init__.py
autograd/torch/nn/functional.py
autograd/torch/nn/module.py
autograd/torch/optim/__init__.py
autograd/torch/optim/lr_scheduler.py
autograd/torch/optim/optimizer.py
test/__init__.py
test/autograd.py
test/test_engine.py
nano_autograds-1.1.1.dist-info/METADATA
nano_autograds-1.1.1.dist-info/WHEEL
nano_autograds-1.1.1.dist-info/top_level.txt
nano_autograds-1.1.1.dist-info/RECORD
